{
    "name": "book.resourcefulbees.apiary_category.apiary_breeder",
    "icon": "resourcefulbees:apiary_breeder",
    "category": "resourcefulbees:apiary",
    "sortnum": 4,
    "pages": [
        {
            "type": "text",
            "text": "book.resourcefulbees.apiary_category.apiary_breeder.1"
        },
        {
            "type": "text",
            "text": "book.resourcefulbees.apiary_category.apiary_breeder.2"
        },
        {
            "type": "text",
            "text": "book.resourcefulbees.apiary_category.apiary_breeder.3"
        },
        {
            "type": "crafting",
            "recipe": "resourcefulbees:apiary_breeder",
            "text": "book.resourcefulbees.apiary_category.apiary_breeder.4"
        },
        {
            "type": "crafting",
            "recipe": "resourcefulbees:apiary_breeder_upgrade",
            "recipe2": "resourcefulbees:apiary_breed_time_upgrade"
        }
    ]
}